{
  "version": "7",
  "dialect": "postgresql",
  "entries": [
    {
      "idx": 0,
      "version": "7",
      "when": 1745392768401,
      "tag": "0000_chunky_rattler",
      "breakpoints": true
    },
    {
      "idx": 1,
      "version": "7",
      "when": 1760466772586,
      "tag": "0001_add_bseq_to_bid_and_lease",
      "breakpoints": true
    },
    {
      "idx": 2,
      "version": "7",
      "when": 1760657218339,
      "tag": "0002_gigantic_ender_wiggin",
      "breakpoints": true
    },
    {
      "idx": 3,
      "version": "7",
      "when": 1762241598822,
      "tag": "0003_add_index_address_transaction_id_on_address_ref",
      "breakpoints": true
    },
    {
      "idx": 4,
      "version": "7",
      "when": 1737331200000,
      "tag": "0004_add_index_transaction_height_desc_index_desc",
      "breakpoints": true
    },
    {
      "idx": 5,
      "version": "7",
      "when": 1737417600000,
      "tag": "0005_add_height_to_address_reference",
      "breakpoints": true
    }
  ]
}